{
    "MonteCarlo" : "singleElectronPass || doubleElectronPass || singleMuonPass || doubleMuonPass || tripleMuonPass || crossEMuPass",
    "EGamma0" : "singleElectronPass || doubleElectronPass",
    "EGamma1" : "singleElectronPass || doubleElectronPass",
    "Muon0" : "(singleMuonPass || doubleMuonPass || tripleMuonPass) && !(singleElectronPass || doubleElectronPass)",
    "Muon1" : "(singleMuonPass || doubleMuonPass || tripleMuonPass) && !(singleElectronPass || doubleElectronPass)",
    "MuonEG" : "crossEMuPass && !(singleMuonPass || doubleMuonPass || tripleMuonPass) && !(singleElectronPass || doubleElectronPass)"
}
